cz_github_convention.py
cz_github_convention-1.0.0.dist-info/LICENSE
cz_github_convention-1.0.0.dist-info/METADATA
cz_github_convention-1.0.0.dist-info/WHEEL
cz_github_convention-1.0.0.dist-info/entry_points.txt
cz_github_convention-1.0.0.dist-info/top_level.txt
cz_github_convention-1.0.0.dist-info/RECORD
