Metadata-Version: 2.1
Name: cz-github-convention
Version: 1.0.0
Summary: Extend the commitizen tools to create conventional commits and README that link to GitHub.
Home-page: https://github.com/evanhongo/cz-github-convention
Author: evanhongo
Author-email: evanhongo@gmail.com
License: MIT
Platform: UNKNOWN
License-File: LICENSE
Requires-Dist: commitizen
